uhdm/_py_uhdm.so
uhdm/__init__.py
uhdm-1.84.dist-info/RECORD
uhdm-1.84.dist-info/WHEEL
uhdm-1.84.dist-info/METADATA
uhdm-1.84.dist-info/licenses/LICENSE
